auth-python/__init__.py
auth-python/auth/__init__.py
auth-python/auth/auth.py
auth-python/codes/__init__.py
auth-python/codes/codes_pb2.py
auth-python/pb/__init__.py
auth-python/pb/gen/__init__.py
auth-python/pb/gen/auth_pb2.py
auth-python/pb/gen/auth_pb2_grpc.py
auth_python/__init__.py
auth_python/auth/__init__.py
auth_python/auth/auth.py
auth_python/codes/__init__.py
auth_python/codes/codes_pb2.py
auth_python/pb/__init__.py
auth_python/pb/gen/__init__.py
auth_python/pb/gen/auth_pb2.py
auth_python/pb/gen/auth_pb2_grpc.py
auth_python-0.0.4.dist-info/METADATA
auth_python-0.0.4.dist-info/WHEEL
auth_python-0.0.4.dist-info/top_level.txt
auth_python-0.0.4.dist-info/RECORD
